{
  "_meta": {
    "schema_version": "1.0",
    "generated_at": "2026-07-23T05:30:54+09:00",
    "overall_status": "complete"
  },
  "stocks": {
    "9432": {
      "price": 152.0,
      "change_pct": 0.1978,
      "mcap_trillion": 12.3764,
      "date": "2026-07-22",
      "status": "ok"
    },
    "9433": {
      "price": 2875.5,
      "change_pct": -0.2082,
      "mcap_trillion": 10.948,
      "date": "2026-07-22",
      "status": "ok"
    },
    "6702": {
      "price": 3311.0,
      "change_pct": 0.0604,
      "mcap_trillion": 5.7438,
      "date": "2026-07-22",
      "status": "ok"
    },
    "6701": {
      "price": 4352.0,
      "change_pct": -1.248,
      "mcap_trillion": 5.7722,
      "date": "2026-07-22",
      "status": "ok"
    },
    "6758": {
      "price": 3444.0,
      "change_pct": -0.4049,
      "mcap_trillion": 20.2248,
      "date": "2026-07-22",
      "status": "ok"
    },
    "9984": {
      "price": 5703.0,
      "change_pct": -0.8346,
      "mcap_trillion": 32.501,
      "date": "2026-07-22",
      "status": "ok"
    },
    "285A": {
      "price": 64270.0,
      "change_pct": 5.2571,
      "mcap_trillion": 35.1713,
      "date": "2026-07-22",
      "status": "ok"
    },
    "6723": {
      "price": 4175.0,
      "change_pct": 3.4696,
      "mcap_trillion": 7.5747,
      "date": "2026-07-22",
      "status": "ok"
    },
    "6526": {
      "price": 2486.5,
      "change_pct": 0.5662,
      "mcap_trillion": 0.4359,
      "date": "2026-07-22",
      "status": "ok"
    },
    "8035": {
      "price": 65960.0,
      "change_pct": -0.9163,
      "mcap_trillion": 29.9888,
      "date": "2026-07-22",
      "status": "ok"
    },
    "6920": {
      "price": 42990.0,
      "change_pct": 0.7499,
      "mcap_trillion": 3.8532,
      "date": "2026-07-22",
      "status": "ok"
    },
    "6857": {
      "price": 29585.0,
      "change_pct": -0.1519,
      "mcap_trillion": 21.4185,
      "date": "2026-07-22",
      "status": "ok"
    },
    "6146": {
      "price": 68590.0,
      "change_pct": 2.6182,
      "mcap_trillion": 7.4398,
      "date": "2026-07-22",
      "status": "ok"
    },
    "7735": {
      "price": 16500.0,
      "change_pct": -2.8269,
      "mcap_trillion": 3.1199,
      "date": "2026-07-22",
      "status": "ok"
    },
    "6525": {
      "price": 8741.0,
      "change_pct": -2.8778,
      "mcap_trillion": 2.0415,
      "date": "2026-07-22",
      "status": "ok"
    },
    "6315": {
      "price": 2860.0,
      "change_pct": 0.4213,
      "mcap_trillion": 0.2146,
      "date": "2026-07-22",
      "status": "ok"
    },
    "6323": {
      "price": 4496.0,
      "change_pct": 3.5229,
      "mcap_trillion": 0.7797,
      "date": "2026-07-22",
      "status": "ok"
    },
    "6254": {
      "price": 4100.0,
      "change_pct": -0.3645,
      "mcap_trillion": 0.157,
      "date": "2026-07-22",
      "status": "ok"
    },
    "7751": {
      "price": 4536.0,
      "change_pct": 0.8,
      "mcap_trillion": 3.8526,
      "date": "2026-07-22",
      "status": "ok"
    },
    "7731": {
      "price": 2212.5,
      "change_pct": 2.0761,
      "mcap_trillion": 0.7288,
      "date": "2026-07-22",
      "status": "ok"
    },
    "4063": {
      "price": 7075.0,
      "change_pct": -1.8043,
      "mcap_trillion": 13.1573,
      "date": "2026-07-22",
      "status": "ok"
    },
    "3436": {
      "price": 3785.0,
      "change_pct": -2.9487,
      "mcap_trillion": 1.3237,
      "date": "2026-07-22",
      "status": "ok"
    },
    "4004": {
      "price": 15250.0,
      "change_pct": 4.5953,
      "mcap_trillion": 2.76,
      "date": "2026-07-22",
      "status": "ok"
    },
    "4062": {
      "price": 18250.0,
      "change_pct": 4.7947,
      "mcap_trillion": 5.0962,
      "date": "2026-07-22",
      "status": "ok"
    },
    "7741": {
      "price": 25045.0,
      "change_pct": -1.5914,
      "mcap_trillion": 8.378,
      "date": "2026-07-22",
      "status": "ok"
    },
    "5384": {
      "price": 4180.0,
      "change_pct": 4.3695,
      "mcap_trillion": 0.3101,
      "date": "2026-07-22",
      "status": "ok"
    },
    "3110": {
      "price": 3180.0,
      "change_pct": 2.2508,
      "mcap_trillion": 0.5788,
      "date": "2026-07-22",
      "status": "ok"
    },
    "6855": {
      "price": 6500.0,
      "change_pct": 2.2013,
      "mcap_trillion": 0.0952,
      "date": "2026-07-22",
      "status": "ok"
    },
    "6890": {
      "price": 7440.0,
      "change_pct": 3.3333,
      "mcap_trillion": 0.4002,
      "date": "2026-07-22",
      "status": "ok"
    },
    "6981": {
      "price": 8317.0,
      "change_pct": 3.9495,
      "mcap_trillion": 15.1393,
      "date": "2026-07-22",
      "status": "ok"
    },
    "6976": {
      "price": 12535.0,
      "change_pct": 6.7263,
      "mcap_trillion": 1.5687,
      "date": "2026-07-22",
      "status": "ok"
    },
    "6762": {
      "price": 3107.0,
      "change_pct": 1.1064,
      "mcap_trillion": 5.8976,
      "date": "2026-07-22",
      "status": "ok"
    },
    "6971": {
      "price": 3780.0,
      "change_pct": 3.1097,
      "mcap_trillion": 4.9077,
      "date": "2026-07-22",
      "status": "ok"
    },
    "6479": {
      "price": 3950.0,
      "change_pct": 1.2301,
      "mcap_trillion": 1.5863,
      "date": "2026-07-22",
      "status": "ok"
    },
    "6997": {
      "price": 3345.0,
      "change_pct": 7.9032,
      "mcap_trillion": 0.0916,
      "date": "2026-07-22",
      "status": "ok"
    },
    "6779": {
      "price": 2850.0,
      "change_pct": 2.9996,
      "mcap_trillion": 0.0653,
      "date": "2026-07-22",
      "status": "ok"
    },
    "5344": {
      "price": 57940.0,
      "change_pct": 2.6032,
      "mcap_trillion": 0.715,
      "date": "2026-07-22",
      "status": "ok"
    },
    "6787": {
      "price": 24390.0,
      "change_pct": 3.6549,
      "mcap_trillion": 0.626,
      "date": "2026-07-22",
      "status": "ok"
    },
    "5803": {
      "price": 4751.0,
      "change_pct": 1.6909,
      "mcap_trillion": 7.866,
      "date": "2026-07-22",
      "status": "ok"
    },
    "5801": {
      "price": 3525.0,
      "change_pct": 3.1003,
      "mcap_trillion": 2.4798,
      "date": "2026-07-22",
      "status": "ok"
    },
    "5802": {
      "price": 2451.0,
      "change_pct": 4.9005,
      "mcap_trillion": 7.6463,
      "date": "2026-07-22",
      "status": "ok"
    },
    "6963": {
      "price": 4785.0,
      "change_pct": 1.0773,
      "mcap_trillion": 1.8472,
      "date": "2026-07-22",
      "status": "ok"
    },
    "6504": {
      "price": 12935.0,
      "change_pct": 2.8628,
      "mcap_trillion": 1.8884,
      "date": "2026-07-22",
      "status": "ok"
    },
    "6503": {
      "price": 5629.0,
      "change_pct": 0.6797,
      "mcap_trillion": 11.5194,
      "date": "2026-07-22",
      "status": "ok"
    },
    "6861": {
      "price": 72110.0,
      "change_pct": 0.2084,
      "mcap_trillion": 17.4885,
      "date": "2026-07-22",
      "status": "ok"
    },
    "6954": {
      "price": 6873.0,
      "change_pct": 1.4315,
      "mcap_trillion": 6.4136,
      "date": "2026-07-22",
      "status": "ok"
    },
    "6506": {
      "price": 5213.0,
      "change_pct": 1.8363,
      "mcap_trillion": 1.3521,
      "date": "2026-07-22",
      "status": "ok"
    },
    "6273": {
      "price": 71850.0,
      "change_pct": 1.9728,
      "mcap_trillion": 4.5171,
      "date": "2026-07-22",
      "status": "ok"
    },
    "6324": {
      "price": 6880.0,
      "change_pct": 4.7184,
      "mcap_trillion": 0.6513,
      "date": "2026-07-22",
      "status": "ok"
    },
    "6594": {
      "price": 2480.0,
      "change_pct": 0.527,
      "mcap_trillion": 2.8428,
      "date": "2026-07-22",
      "status": "ok"
    },
    "6645": {
      "price": 5463.0,
      "change_pct": 1.9597,
      "mcap_trillion": 1.0742,
      "date": "2026-07-22",
      "status": "ok"
    },
    "3778": {
      "price": 2906.0,
      "change_pct": 2.9766,
      "mcap_trillion": 0.1163,
      "date": "2026-07-22",
      "status": "ok"
    },
    "3905": {
      "price": 2419.0,
      "change_pct": -3.6639,
      "mcap_trillion": 0.0772,
      "date": "2026-07-22",
      "status": "ok"
    },
    "6501": {
      "price": 4807.0,
      "change_pct": 0.313,
      "mcap_trillion": 21.5566,
      "date": "2026-07-22",
      "status": "ok"
    }
  }
}